dataflow_ext/__init__.py
dataflow_ext/main.py
dataflow_ext/pub_sub.py
dataflow_ext-0.1.1.dist-info/METADATA
dataflow_ext-0.1.1.dist-info/WHEEL
dataflow_ext-0.1.1.dist-info/licenses/LICENSE
dataflow_ext-0.1.1.dist-info/RECORD
